AUTHORS.rst
CONTRIBUTING.rst
HISTORY.rst
LICENSE
MANIFEST.in
README.rst
setup.cfg
setup.py
docs/Makefile
docs/authors.rst
docs/conf.py
docs/contributing.rst
docs/history.rst
docs/index.rst
docs/installation.rst
docs/make.bat
docs/readme.rst
docs/usage.rst
jarvispatrick/__init__.py
jarvispatrick.egg-info/PKG-INFO
jarvispatrick.egg-info/SOURCES.txt
jarvispatrick.egg-info/dependency_links.txt
jarvispatrick.egg-info/not-zip-safe
jarvispatrick.egg-info/pbr.json
jarvispatrick.egg-info/top_level.txt
tests/__init__.py
tests/test_jarvispatrick.py