Metadata-Version: 1.1
Name: jarvispatrick
Version: 0.1.2
Summary: Jarvis-Patrick Clustering that uses a nearest neighbor approach to clustering objects
Home-page: https://github.com/llazzaro/jarvispatrick
Author: Leonardo Lazzaro
Author-email: llazzaro@dc.uba.ar
License: ISCL
Keywords: jarvispatrick
Platform: UNKNOWN
Classifier: Development Status :: 2 - Pre-Alpha
Classifier: Intended Audience :: Developers
Classifier: License :: OSI Approved :: ISC License (ISCL)
Classifier: Natural Language :: English
Classifier: Programming Language :: Python :: 2
Classifier: Programming Language :: Python :: 2.6
Classifier: Programming Language :: Python :: 2.7
Classifier: Programming Language :: Python :: 3
Classifier: Programming Language :: Python :: 3.3
Classifier: Programming Language :: Python :: 3.4
Classifier: Programming Language :: Python :: 3.5
